batutils/__init__.py
batutils/_common/__init__.py
batutils/_common/_decode.py
batutils/dtu/__init__.py
batutils/dtu/casting/__init__.py
batutils/dtu/casting/_any.py
batutils/dtu/casting/_filetime.py
batutils/dtu/casting/_instant.py
batutils/dtu/casting/_string.py
batutils/dtu/casting/_timestamp.py
batutils/dtu/formatting/__init__.py
batutils/dtu/formatting/_delta.py
batutils/dtu/formatting/_serialize.py
batutils/dtu/parsers/__init__.py
batutils/dtu/parsers/_string.py
batutils/dtu/parsers/_timedelta.py
batutils/dtu/shortcuts/__init__.py
batutils/dtu/shortcuts/_aliases.py
batutils/dtu/shortcuts/_checkers.py
batutils/dtu/shortcuts/_finders.py
batutils/dtu/structs/__init__.py
batutils/dtu/structs/_base.py
batutils/dtu/structs/_deltasplit.py
batutils/dtu/structs/_types.py
batutils/dtu/structs/aliases.py
batutils/dtu/structs/consts.py
batutils/structs/__init__.py
batutils/structs/_base.py
batutils/tpu/__init__.py
batutils/tpu/casting/__init__.py
batutils/tpu/casting/_currency.py
batutils/tpu/casting/_evals.py
batutils/tpu/casting/_ip.py
batutils/tpu/casting/_mask.py
batutils/tpu/casting/_params.py
batutils/tpu/casting/_serialize.py
batutils/tpu/comparison/__init__.py
batutils/tpu/comparison/_mixin.py
batutils/tpu/insp/__init__.py
batutils/tpu/insp/_insp_old.py
batutils/tpu/insp/_typecheck.py
batutils/tpu/iters/__init__.py
batutils/tpu/iters/_attrs.py
batutils/tpu/iters/_dicts.py
batutils/tpu/iters/_group.py
batutils/tpu/iters/_lists.py
batutils/tpu/size/__init__.py
batutils/tpu/size/_total.py
batutils/tpu/strimp/__init__.py
batutils/tpu/strimp/_getters.py
batutils/tpu/string/__init__.py
batutils/tpu/string/_string.py
batutils/tpu/structs/__init__.py
batutils/tpu/structs/_base.py
batutils/tpu/structs/empty/__init__.py
batutils/tpu/structs/empty/_empty.py
batutils/tpu/structs/enumex/__init__.py
batutils/tpu/structs/enumex/_enumextra.py
batutils/tpu/structs/fluid/__init__.py
batutils/tpu/structs/fluid/_attrfluid.py
batutils/tpu/structs/sentience/__init__.py
batutils-2.1.0.dist-info/LICENSE
batutils-2.1.0.dist-info/METADATA
batutils-2.1.0.dist-info/WHEEL
batutils-2.1.0.dist-info/top_level.txt
batutils-2.1.0.dist-info/RECORD
